Hdecompose/BlitzRosolowsky2006.py
Hdecompose/RahmatiEtal2013.py
Hdecompose/SpringelHernquist2003.py
Hdecompose/__init__.py
Hdecompose/__version__.py
Hdecompose/atomic_frac.py
hdecompose-0.1.0.dist-info/LICENSE.md
hdecompose-0.1.0.dist-info/METADATA
hdecompose-0.1.0.dist-info/WHEEL
hdecompose-0.1.0.dist-info/top_level.txt
hdecompose-0.1.0.dist-info/RECORD
