Metadata-Version: 2.1
Name: hdecompose
Version: 0.1.0
Summary: Hydrogen decomposition to HI, H2.
Author-email: Kyle Oman <kyle.a.oman@durham.ac.uk>
Project-URL: Homepage, https://github.com/kyleaoman/eagleSqlTools
Project-URL: Bug Tracker, https://github.com/kyleaoman/eagleSqlTools/issues
Classifier: Programming Language :: Python :: 3
Classifier: License :: OSI Approved :: GNU General Public License v3 (GPLv3)
Classifier: Operating System :: OS Independent
Requires-Python: >=3.7
License-File: LICENSE.md
Requires-Dist: numpy
Requires-Dist: astropy
